prectime/__init__.py
prectime-0.0.3.dist-info/LICENSE
prectime-0.0.3.dist-info/METADATA
prectime-0.0.3.dist-info/WHEEL
prectime-0.0.3.dist-info/top_level.txt
prectime-0.0.3.dist-info/RECORD
