Metadata-Version: 2.1
Name: prectime
Version: 0.0.3
Summary: precious time
Author-email: classno <classno@gmail.com>
Project-URL: Homepage, https://github.com/classno/prectime
Project-URL: Bug Tracker, https://github.com/classno/prectime/issues
Classifier: Programming Language :: Python :: 3
Classifier: License :: OSI Approved :: MIT License
Classifier: Operating System :: OS Independent
Requires-Python: >=3.7
License-File: LICENSE
